feed/__init__.py
feed/api/__init__.py
feed/api/boolean/__init__.py
feed/api/boolean/operations.py
feed/api/float/__init__.py
feed/api/float/accumulators.py
feed/api/float/imputation.py
feed/api/float/operations.py
feed/api/float/ordering.py
feed/api/float/utils.py
feed/api/float/window/__init__.py
feed/api/float/window/ewm.py
feed/api/float/window/expanding.py
feed/api/float/window/rolling.py
feed/api/generic/__init__.py
feed/api/generic/imputation.py
feed/api/generic/operators.py
feed/api/generic/reduce.py
feed/api/generic/warmup.py
feed/api/string/__init__.py
feed/api/string/operations.py
feed/core/__init__.py
feed/core/accessors.py
feed/core/base.py
feed/core/feed.py
feed/core/methods.py
feed/core/mixins.py
feed/core/operators.py
tests/api/__init__.py
tests/api/float/__init__.py
tests/api/float/test_accumulators.py
tests/api/float/test_imputations.py
tests/api/float/test_operations.py
tests/api/float/test_ordering.py
tests/api/float/test_utils.py
tests/api/float/window/__init__.py
tests/api/float/window/test_ewm.py
tests/api/float/window/test_expanding.py
tests/api/float/window/test_rolling.py
tests/api/generic/__init__.py
tests/api/generic/test_reduce.py
tests/core/__init__.py
tests/core/test_base.py
tests/core/test_boolean.py
tests/core/test_float.py
tests/core/test_generic.py
tests/core/test_str.py
tests/utils/__init__.py
tests/utils/ops.py
feed_stream-0.0.2.dist-info/LICENSE
feed_stream-0.0.2.dist-info/METADATA
feed_stream-0.0.2.dist-info/WHEEL
feed_stream-0.0.2.dist-info/top_level.txt
feed_stream-0.0.2.dist-info/RECORD
